certbot_dns_njalla/__init__.py
certbot_dns_njalla/dns_njalla.py
certbot_dns_njalla/dns_njalla_test.py
certbot_dns_njalla-2.0.2.dist-info/LICENSE
certbot_dns_njalla-2.0.2.dist-info/METADATA
certbot_dns_njalla-2.0.2.dist-info/WHEEL
certbot_dns_njalla-2.0.2.dist-info/entry_points.txt
certbot_dns_njalla-2.0.2.dist-info/top_level.txt
certbot_dns_njalla-2.0.2.dist-info/RECORD
