Metadata-Version: 2.1
Name: certbot-dns-njalla
Version: 2.0.2
Summary: Njalla DNS Authenticator plugin for Certbot
Author: chaptergy
License:                                  Apache License
Project-URL: Repository, https://github.com/chaptergy/certbot-dns-njalla.git
Keywords: certbot,njalla,dns,certificate,SSL,TLS
Classifier: Development Status :: 4 - Beta
Classifier: Environment :: Plugins
Classifier: Intended Audience :: System Administrators
Classifier: License :: OSI Approved :: Apache Software License
Classifier: Programming Language :: Python
Classifier: Programming Language :: Python :: 3
Classifier: Topic :: Internet :: WWW/HTTP
Classifier: Topic :: Security
Classifier: Topic :: System :: Installation/Setup
Classifier: Topic :: System :: Networking
Classifier: Topic :: Internet :: Name Service (DNS)
Classifier: Topic :: System :: Systems Administration
Classifier: Topic :: Utilities
License-File: LICENSE
Requires-Dist: certbot>=3.0.0
Requires-Dist: dns-lexicon>=3.14.1
Provides-Extra: test
Requires-Dist: mock; extra == "test"
Requires-Dist: requests; extra == "test"
